README.rst
s3upload.py
setup.py
s3upload.egg-info/PKG-INFO
s3upload.egg-info/SOURCES.txt
s3upload.egg-info/dependency_links.txt
s3upload.egg-info/entry_points.txt
s3upload.egg-info/requires.txt
s3upload.egg-info/top_level.txt