Metadata-Version: 1.0
Name: s3upload
Version: 0.2.4
Summary: A python module for uploading data to s3 using the s3 multipart API
Home-page: https://github.com/leetreveil/pys3upload
Author: Lee Treveil
Author-email: leetreveil@gmail.com
License: MIT
Keywords: s3,multipart,upload,amazon
Platform: UNKNOWN
